src/__init__.py
src/server.py
readium_mcp-0.2.0.dist-info/LICENSE
readium_mcp-0.2.0.dist-info/METADATA
readium_mcp-0.2.0.dist-info/WHEEL
readium_mcp-0.2.0.dist-info/entry_points.txt
readium_mcp-0.2.0.dist-info/RECORD
