Metadata-Version: 2.3
Name: readium-mcp
Version: 0.2.0
Summary: MCP server that exposes Readium's functionality for document analysis
Author: Pablo Toledo
Author-email: pablotoledo@users.noreply.github.com
Requires-Python: >=3.10,<4.0
Classifier: Programming Language :: Python :: 3
Classifier: Programming Language :: Python :: 3.10
Classifier: Programming Language :: Python :: 3.11
Classifier: Programming Language :: Python :: 3.12
Classifier: Programming Language :: Python :: 3.13
Requires-Dist: mcp[cli] (>=1.8.0,<2.0.0)
Requires-Dist: readium (>=0.4.1,<0.5.0)
